jax_metrics/__init__.py
jax_metrics/losses/__init__.py
jax_metrics/losses/cosine_similarity.py
jax_metrics/losses/crossentropy.py
jax_metrics/losses/huber.py
jax_metrics/losses/loss.py
jax_metrics/losses/mean_absolute_error.py
jax_metrics/losses/mean_absolute_percentage_error.py
jax_metrics/losses/mean_squared_error.py
jax_metrics/losses/mean_squared_logarithmic_error.py
jax_metrics/metrics/__init__.py
jax_metrics/metrics/accuracy.py
jax_metrics/metrics/losses.py
jax_metrics/metrics/mean.py
jax_metrics/metrics/mean_absolute_error.py
jax_metrics/metrics/mean_square_error.py
jax_metrics/metrics/metric.py
jax_metrics/metrics/metrics.py
jax_metrics/metrics/reduce.py
jax_metrics/metrics/tm_port/__init__.py
jax_metrics/metrics/tm_port/classification/__init__.py
jax_metrics/metrics/tm_port/classification/accuracy.py
jax_metrics/metrics/tm_port/classification/stat_scores.py
jax_metrics/metrics/tm_port/functional/__init__.py
jax_metrics/metrics/tm_port/functional/classification/__init__.py
jax_metrics/metrics/tm_port/functional/classification/accuracy.py
jax_metrics/metrics/tm_port/functional/classification/stat_scores.py
jax_metrics/metrics/tm_port/utilities/__init__.py
jax_metrics/metrics/tm_port/utilities/checks.py
jax_metrics/metrics/tm_port/utilities/data.py
jax_metrics/metrics/tm_port/utilities/distributed.py
jax_metrics/metrics/tm_port/utilities/enums.py
jax_metrics/metrics/tm_port/utilities/exceptions.py
jax_metrics/metrics/tm_port/utilities/imports.py
jax_metrics/metrics/tm_port/utilities/prints.py
jax_metrics/metrics/utils.py
jax_metrics/regularizers/__init__.py
jax_metrics/regularizers/l1l2.py
jax_metrics/types.py
jax_metrics/utils.py
jax_metrics-0.2.5.dist-info/LICENSE
jax_metrics-0.2.5.dist-info/METADATA
jax_metrics-0.2.5.dist-info/WHEEL
jax_metrics-0.2.5.dist-info/RECORD
