Metadata-Version: 2.1
Name: jax-metrics
Version: 0.2.5
Summary: 
Home-page: https://cgarciae.github.io/jax_metrics
License: MIT
Author: Cristian Garcia
Author-email: cgarcia.e88@gmail.com
Requires-Python: >=3.8,<3.12
Classifier: License :: OSI Approved :: MIT License
Classifier: Programming Language :: Python :: 3
Classifier: Programming Language :: Python :: 3.8
Classifier: Programming Language :: Python :: 3.9
Classifier: Programming Language :: Python :: 3.10
Classifier: Programming Language :: Python :: 3.11
Requires-Dist: einops (>=0.4.0)
Requires-Dist: jax
Requires-Dist: jaxlib
Requires-Dist: optax (>=0.1.1)
Requires-Dist: simple_pytree (>=0.1.3)
Project-URL: Repository, https://github.com/cgarciae/jax_metrics
